adm/__init__.py
adm/adm_classes.py
adm/adm_const.py
adm/adm_tool.py
am_viewer/__init__.py
am_viewer/am_viewer_main.py
am_viewer/am_xml_viewer.py
am_viewer/adm/__init__.py
am_viewer/adm/adm_classes.py
am_viewer/adm/adm_const.py
am_viewer/adm/adm_tool.py
am_viewer/aoip_services/__init__.py
am_viewer/aoip_services/aoip_discovery.py
am_viewer/aoip_services/multicast.py
am_viewer/aoip_services/sdp_parser.py
am_viewer/pmd/__init__.py
am_viewer/pmd/pmd_classes.py
am_viewer/pmd/pmd_const.py
am_viewer/pmd/pmd_tool.py
am_viewer-4.1.9.dist-info/licenses/LICENSE
aoip_services/__init__.py
aoip_services/aoip_discovery.py
aoip_services/multicast.py
aoip_services/sdp_parser.py
pmd/__init__.py
pmd/pmd_classes.py
pmd/pmd_const.py
pmd/pmd_tool.py
am_viewer-4.1.9.dist-info/METADATA
am_viewer-4.1.9.dist-info/WHEEL
am_viewer-4.1.9.dist-info/entry_points.txt
am_viewer-4.1.9.dist-info/top_level.txt
am_viewer-4.1.9.dist-info/RECORD
