Metadata-Version: 2.4
Name: am_viewer
Version: 4.1.9
Summary: A ST2110-31/41 Serial ADM audio metadata real-time viewer as specified in Recommendation ITU-R BS.2125, ST 2116, ST 2127-2,
Author-email: James Cowdery <jtc@dolby.com>
Classifier: Programming Language :: Python :: 3
Classifier: Operating System :: OS Independent
Requires-Python: >=3
License-File: LICENSE
Requires-Dist: zeroconf<=0.26.3
Requires-Dist: scapy>=2.5.0
Dynamic: license-file
